ai_haley_ml_domain/__init__.py
ai_haley_ml_domain/domain-ontology/haley-ai-ml-0.1.0.owl
ai_haley_ml_domain/model/ActorMindRequest.py
ai_haley_ml_domain/model/ActorMindRequest.pyi
ai_haley_ml_domain/model/AddContextMindRequest.py
ai_haley_ml_domain/model/AddContextMindRequest.pyi
ai_haley_ml_domain/model/DomainOntology.py
ai_haley_ml_domain/model/Edge_hasFeatureValue.py
ai_haley_ml_domain/model/Edge_hasFeatureValue.pyi
ai_haley_ml_domain/model/Edge_hasHaleyIntentSlot.py
ai_haley_ml_domain/model/Edge_hasHaleyIntentSlot.pyi
ai_haley_ml_domain/model/Edge_hasHaleyIntentSlotIntance.py
ai_haley_ml_domain/model/Edge_hasHaleyIntentSlotIntance.pyi
ai_haley_ml_domain/model/Edge_hasPredictionModel.py
ai_haley_ml_domain/model/Edge_hasPredictionModel.pyi
ai_haley_ml_domain/model/Edge_hasPredictionModelInput.py
ai_haley_ml_domain/model/Edge_hasPredictionModelInput.pyi
ai_haley_ml_domain/model/Edge_hasPrompt.py
ai_haley_ml_domain/model/Edge_hasPrompt.pyi
ai_haley_ml_domain/model/Edge_hasPromptInput.py
ai_haley_ml_domain/model/Edge_hasPromptInput.pyi
ai_haley_ml_domain/model/Edge_hasRecommendationModel.py
ai_haley_ml_domain/model/Edge_hasRecommendationModel.pyi
ai_haley_ml_domain/model/Edge_hasRecommendationModelInput.py
ai_haley_ml_domain/model/Edge_hasRecommendationModelInput.pyi
ai_haley_ml_domain/model/Edge_hasSelectedPredictionModel.py
ai_haley_ml_domain/model/Edge_hasSelectedPredictionModel.pyi
ai_haley_ml_domain/model/Edge_hasSelectedPrompt.py
ai_haley_ml_domain/model/Edge_hasSelectedPrompt.pyi
ai_haley_ml_domain/model/Edge_hasSelectedRecommendationModel.py
ai_haley_ml_domain/model/Edge_hasSelectedRecommendationModel.pyi
ai_haley_ml_domain/model/Edge_hasTargetValue.py
ai_haley_ml_domain/model/Edge_hasTargetValue.pyi
ai_haley_ml_domain/model/FeatureGroup.py
ai_haley_ml_domain/model/FeatureGroup.pyi
ai_haley_ml_domain/model/FeatureType.py
ai_haley_ml_domain/model/FeatureType.pyi
ai_haley_ml_domain/model/FeatureValue.py
ai_haley_ml_domain/model/FeatureValue.pyi
vital_ai_haley_ml-0.1.6.dist-info/METADATA
vital_ai_haley_ml-0.1.6.dist-info/WHEEL
vital_ai_haley_ml-0.1.6.dist-info/entry_points.txt
vital_ai_haley_ml-0.1.6.dist-info/top_level.txt
vital_ai_haley_ml-0.1.6.dist-info/RECORD
