Metadata-Version: 2.1
Name: vital-ai-haley-ml
Version: 0.1.6
Summary: VitalSigns haley ml domain
Home-page: https://github.com/vital-ai/vitalhome-haley
Author: Marc Hadfield
Author-email: marc@vital.ai
License: Apache License 2.0
Classifier: Programming Language :: Python :: 3.10
Classifier: License :: OSI Approved :: Apache Software License
Classifier: Operating System :: OS Independent
Requires-Python: >=3.10
Requires-Dist: vital-ai-haley>=0.1.6
